{
  "themeDictionary": {
    "cal": "Cal",
    "classic": "Classic",
    "dark": "Dark",
    "light": "Light"
  },
  "theme": "light",

  "layoutDictionary": { "default": "Default" },
  "layout": "default",

  "languageDictionary": { "cn": "🇨🇳 简体中文", "en": "🇺🇸 English" },
  "language": "en",

  "serverDataVersion": "1",
  "serverDataSource": "https://nyc.cs.berkeley.edu/universal/v1",
  "turn0Name": "Left Player",
  "turn1Name": "Right Player",
  "vvhSelectorId": "app-game-vvh-canvas",

  "gameInstructionVisibility": false,
  "gameOptionsVisibility": false,
  "clockVisibility": false,
  "vvhVisibility": false,
  "nextMovesVisibility": false,
  "hintVisibility": false,
  "deltaRemotenessVisibility": false,
  "animationDuration": 1,

  "gitHubDataSource": "https://api.github.com/repos/gamescrafters/gamesmanuni",

  "maximumRemoteness": 6,

  "vvhXLabel": "Remoteness",
  "vvhYLeftLabel": "Moves",
  "vvhYRightLabel": "Moves",

  "vvhPadding": 10,
  "vvhTurnNameHeight": 20,
  "vvhXLabelHeight": 20,
  "vvhXCoordinateHeight": 20,
  "vvhRowHeight": 20,

  "vvhYLabelWidth": 20,
  "vvhYCoordinateWidth": 40,
  "vvhColumnWidth": 10,

  "vvhPointRadius": 5,
  "vvhLinkWidth": 1,
  "vvhXBarWidth": 1,
  "vvhXIntervalBarWidth": 2,
  "vvhXInterval": 5
}
